ottic/__init__.py
ottic/constants.py
ottic/main.py
ottic/client/__init__.py
ottic/client/client.py
ottic/modules/__init__.py
ottic/modules/chat.py
ottic/modules/completions.py
ottic/modules/prompt.py
ottic/utils/__init__.py
ottic/utils/response_format.py
ottic-0.1.3.dist-info/LICENSE
ottic-0.1.3.dist-info/METADATA
ottic-0.1.3.dist-info/WHEEL
ottic-0.1.3.dist-info/top_level.txt
ottic-0.1.3.dist-info/RECORD
