Metadata-Version: 2.2
Name: ottic
Version: 0.1.3
Summary: SDK for Ottic API
Author-email: Dmitry Sergeev <dmitry@ottic.ai>
Project-URL: Homepage, https://ottic.ai
Project-URL: Issues, https://github.com/ottic-ai/ottic-py
Classifier: Programming Language :: Python :: 3
Classifier: License :: OSI Approved :: MIT License
Classifier: Operating System :: OS Independent
Requires-Python: >=3.8
License-File: LICENSE
Requires-Dist: requests
Requires-Dist: pydantic
Requires-Dist: docstring_parser
